extract2md/__init__.py
extract2md/__main__.py
extract2md/_fetch.py
extract2md/_html.py
extract2md/_links.py
extract2md/_version.py
extract2md/cli.py
extract2md/core.py
extract2md/models.py
extract2md/converters/__init__.py
extract2md/converters/readability.py
extract2md/converters/trafilatura.py
extract2md-0.1.2.dist-info/METADATA
extract2md-0.1.2.dist-info/WHEEL
extract2md-0.1.2.dist-info/entry_points.txt
extract2md-0.1.2.dist-info/licenses/LICENSE
extract2md-0.1.2.dist-info/RECORD
