Metadata-Version: 2.4
Name: extract2md
Version: 0.1.2
Summary: Fetch a web page and convert it into cleaned Markdown.
Project-URL: Homepage, https://github.com/Wuodan/extract2md
Project-URL: Repository, https://github.com/Wuodan/extract2md
Project-URL: Issues, https://github.com/Wuodan/extract2md/issues
License: MIT
License-File: LICENSE
Requires-Python: >=3.10
Requires-Dist: beautifulsoup4>=4.12
Requires-Dist: httpx>=0.25
Requires-Dist: markdownify>=0.13
Requires-Dist: protego>=0.3
Requires-Dist: readabilipy>=0.2
Requires-Dist: trafilatura>=1.6
